dash_lazy_load/__init__.py
dash_lazy_load/bundle.js
dash_lazy_load/lodash.min.js
dash_lazy_load/metadata.json
dash_lazy_load/version.py
dash_lazy_load-1.3.1.dist-info/LICENSE.txt
dash_lazy_load-1.3.1.dist-info/METADATA
dash_lazy_load-1.3.1.dist-info/WHEEL
dash_lazy_load-1.3.1.dist-info/top_level.txt
dash_lazy_load-1.3.1.dist-info/RECORD
