Metadata-Version: 2.1
Name: dash-lazy-load
Version: 1.3.1
Summary: Dash implementation of react-lazyload
Home-page: UNKNOWN
Author: StratoDem
Author-email: UNKNOWN
License: MIT
Platform: UNKNOWN
